pyfilemeta/__init__.py
pyfilemeta/metadata.py
PyMetaFile-0.1.0.dist-info/LICENSE
PyMetaFile-0.1.0.dist-info/METADATA
PyMetaFile-0.1.0.dist-info/WHEEL
PyMetaFile-0.1.0.dist-info/top_level.txt
PyMetaFile-0.1.0.dist-info/RECORD
