Metadata-Version: 2.2
Name: PyMetaFile
Version: 0.1.0
Summary: A library for extracting metadata from files
Home-page: https://github.com/darioajr/pyfilemeta
Author: Dario Alves Junior
Author-email: darioajr@gmail.com
License: MIT
Classifier: Programming Language :: Python :: 3
Classifier: License :: OSI Approved :: MIT License
Classifier: Operating System :: OS Independent
Requires-Python: >=3.1
License-File: LICENSE
Provides-Extra: dev
Requires-Dist: pytest; extra == "dev"
Requires-Dist: build; extra == "dev"
Requires-Dist: twine; extra == "dev"
